ThodarKuri/Filler.py
ThodarKuri/Parser.py
ThodarKuri/__init__.py
ThodarKuri/Grammer/SyntaxParser.py
ThodarKuri/Grammer/__init__.py
ThodarKuri-1.0.0.dist-info/LICENSE.txt
ThodarKuri-1.0.0.dist-info/METADATA
ThodarKuri-1.0.0.dist-info/WHEEL
ThodarKuri-1.0.0.dist-info/top_level.txt
ThodarKuri-1.0.0.dist-info/RECORD
