Metadata-Version: 2.1
Name: ThodarKuri
Version: 1.0.0
Summary: Generic Recursive Template Engine for Parsing and Filling
Home-page: https://github.com/Palani-SN/ThodarKuri
Author: Palani-SN
Author-email: psn396@gmail.com
License: UNKNOWN
Platform: UNKNOWN
Classifier: Programming Language :: Python :: 3
Classifier: Programming Language :: Python :: 3.7
Classifier: License :: OSI Approved :: GNU General Public License v3 or later (GPLv3+)
Classifier: Operating System :: OS Independent
Requires-Dist: blessings (~=1.7)
Requires-Dist: lark (>=1.0.0)
Provides-Extra: dev
Requires-Dist: pytest (>=3.7) ; extra == 'dev'
Requires-Dist: check-manifest ; extra == 'dev'
Requires-Dist: twine ; extra == 'dev'
Requires-Dist: requests (>=2.26.0) ; extra == 'dev'
